{"AppConfig": [{"id":  "6d4f4f4f-32f0-4e2d-a79b-01dae03f035e" ,"createdAt":  "2023-08-06T07:25:55.000Z" ,"updatedAt":  "2022-02-13T23:34:57.000Z" ,"value":  "nstmgvy2db" ,"key":  "ke9k5l2twh" },{"id":  "ea8753e7-9f55-4cb5-b839-af67a9c2ec15" ,"createdAt":  "2022-09-16T20:57:21.000Z" ,"updatedAt":  "2021-11-21T13:05:26.000Z" ,"value":  "w7qjrknyek" ,"key":  "lzbocui2y5" },{"id":  "310b0578-60e1-4400-b3d4-5ac76b5ca26f" ,"createdAt":  "2022-05-02T02:30:18.000Z" ,"updatedAt":  "2021-11-03T14:25:02.000Z" ,"value":  "iyp8migg1l" ,"key":  "s95b5psf96" },{"id":  "611bd30c-f829-4692-97a2-2e07370e78f9" ,"createdAt":  "2023-09-10T16:22:48.000Z" ,"updatedAt":  "2022-05-18T09:27:07.000Z" ,"value":  "m1rajpyd2w" ,"key":  "biiqefgvx7" },{"id":  "88e58d05-3b18-4157-b570-f9915524aeb8" ,"createdAt":  "2022-12-18T08:56:43.000Z" ,"updatedAt":  "2022-04-23T15:03:56.000Z" ,"value":  "8g8imu6l2j" ,"key":  "jn5c7eypr8" },{"id":  "853899fe-563c-4d67-9830-909ab44713c2" ,"createdAt":  "2022-05-04T15:29:37.000Z" ,"updatedAt":  "2022-09-23T09:27:09.000Z" ,"value":  "c3y4ykjgng" ,"key":  "lrczg32tp1" },{"id":  "3a262d0c-6a95-4ca9-806a-0d2f7a1b3278" ,"createdAt":  "2023-10-07T01:04:09.000Z" ,"updatedAt":  "2022-10-24T06:53:54.000Z" ,"value":  "5p1b3dh3s5" ,"key":  "kyq1fe3jzo" },{"id":  "3ce564b4-cf7e-4c7e-828f-2b6edb78dd93" ,"createdAt":  "2023-01-23T18:03:20.000Z" ,"updatedAt":  "2022-06-25T00:49:05.000Z" ,"value":  "nv7tqqg061" ,"key":  "qo9if3fykw" },{"id":  "c2a88fe0-0e54-4d64-b825-02963a04d062" ,"createdAt":  "2022-06-28T21:12:25.000Z" ,"updatedAt":  "2023-09-28T07:16:51.000Z" ,"value":  "0tt87jznhd" ,"key":  "ktyju07vjx" },{"id":  "1832c46e-0115-46f9-95b6-520376939df7" ,"createdAt":  "2023-05-30T09:04:18.000Z" ,"updatedAt":  "2022-09-02T23:52:33.000Z" ,"value":  "kjdajhcphj" ,"key":  "a74r7q9i6q" },{"id":  "9a207b85-b4ca-4843-bb11-57f38063b8fd" ,"createdAt":  "2022-10-22T14:20:50.000Z" ,"updatedAt":  "2021-12-14T19:25:22.000Z" ,"value":  "hd6pqoq7g2" ,"key":  "hvnkmqdj1i" },{"id":  "725afdae-1b6c-43dd-b71a-94b63e78dad1" ,"createdAt":  "2023-02-16T07:23:15.000Z" ,"updatedAt":  "2022-09-15T02:38:06.000Z" ,"value":  "ye63p2mk18" ,"key":  "v5sje632or" },{"id":  "422e4acf-44e8-464f-bffb-9f0b858a1b8f" ,"createdAt":  "2022-04-04T02:12:41.000Z" ,"updatedAt":  "2022-07-29T02:19:43.000Z" ,"value":  "qpuy7tunab" ,"key":  "or9gm9ydeb" },{"id":  "f5c546b9-522e-4713-be05-44a798889db3" ,"createdAt":  "2021-11-26T04:54:54.000Z" ,"updatedAt":  "2021-10-28T00:04:20.000Z" ,"value":  "mctgahlsuh" ,"key":  "th0742k5e3" },{"id":  "e458d615-e4ed-4854-a5d9-7c302ca5870c" ,"createdAt":  "2022-07-03T14:09:29.000Z" ,"updatedAt":  "2023-10-04T10:04:38.000Z" ,"value":  "nqlmpc3kh4" ,"key":  "u9bjwlvbz5" },{"id":  "685eb04b-97c9-4d92-857d-e32aa6501f90" ,"createdAt":  "2022-02-01T20:54:03.000Z" ,"updatedAt":  "2023-02-02T20:36:42.000Z" ,"value":  "w4weh1pm0z" ,"key":  "3xfd7azyyx" },{"id":  "ac86408c-89b3-4a12-a150-c7d63f466b5f" ,"createdAt":  "2023-08-30T05:06:32.000Z" ,"updatedAt":  "2022-12-28T18:43:50.000Z" ,"value":  "fl7bnqzqtp" ,"key":  "oobbjvxpx0" },{"id":  "6c075963-b964-4af7-8f66-4603c8a7fed7" ,"createdAt":  "2023-06-16T09:37:34.000Z" ,"updatedAt":  "2022-03-23T23:25:20.000Z" ,"value":  "7lbbiispmw" ,"key":  "dcruys12y0" },{"id":  "4da4b100-6a8b-4f6b-971a-296e36d75b84" ,"createdAt":  "2023-04-26T20:53:13.000Z" ,"updatedAt":  "2022-04-27T01:37:39.000Z" ,"value":  "idpotpnuq4" ,"key":  "gkvzqriv1v" },{"id":  "612aa10a-25dc-47d0-b2cd-5b9b800d138b" ,"createdAt":  "2022-08-29T13:50:16.000Z" ,"updatedAt":  "2022-03-01T07:42:26.000Z" ,"value":  "u2haa8wf0r" ,"key":  "psi7922oxe" },{"id":  "f246eff9-370f-4e52-bc0a-7a937873d36e" ,"createdAt":  "2023-07-11T18:22:36.000Z" ,"updatedAt":  "2022-05-21T14:16:11.000Z" ,"value":  "4j3xrdeovm" ,"key":  "x636i1r0rp" },{"id":  "7e15781f-a71e-4577-9d89-9d24a8caa10e" ,"createdAt":  "2022-01-22T15:45:39.000Z" ,"updatedAt":  "2023-06-09T06:20:47.000Z" ,"value":  "d6lk1mtu7y" ,"key":  "ramlvmbxvq" },{"id":  "dbf03c79-313d-4d23-88ca-06add4471ebc" ,"createdAt":  "2022-03-12T22:21:30.000Z" ,"updatedAt":  "2023-09-08T21:05:28.000Z" ,"value":  "a9y3nuqenv" ,"key":  "58efr4ueiq" },{"id":  "6c74571c-8427-4ea3-981f-3d6251c39fd6" ,"createdAt":  "2022-08-15T09:34:46.000Z" ,"updatedAt":  "2021-12-10T09:55:09.000Z" ,"value":  "zxehl4w6k6" ,"key":  "4cp9qe4jq2" },{"id":  "129c761b-017e-4a29-aa46-f1da49f6890b" ,"createdAt":  "2023-05-12T06:22:17.000Z" ,"updatedAt":  "2023-09-21T14:53:08.000Z" ,"value":  "wuci2c4fe4" ,"key":  "lwbefzn9sa" },{"id":  "a8b8de5d-c180-4e08-99ac-19844b1f9109" ,"createdAt":  "2023-08-17T08:24:58.000Z" ,"updatedAt":  "2022-02-03T05:56:42.000Z" ,"value":  "fc6rlyqpvb" ,"key":  "4pvpjg6z3d" },{"id":  "549aeb9d-9479-4312-b456-a6ba9fbdbbb9" ,"createdAt":  "2023-03-28T11:48:38.000Z" ,"updatedAt":  "2021-10-17T12:03:33.000Z" ,"value":  "cecvlc9m2i" ,"key":  "ockvi0fhsy" },{"id":  "567cb624-3ba2-4865-9331-2f37717078f0" ,"createdAt":  "2021-12-07T14:32:48.000Z" ,"updatedAt":  "2022-12-15T13:24:19.000Z" ,"value":  "5ow1lzktv1" ,"key":  "aawqdzixop" },{"id":  "f59f1531-c674-4e21-9ddf-cb8ab51e4d66" ,"createdAt":  "2023-05-23T04:39:07.000Z" ,"updatedAt":  "2022-04-29T05:09:54.000Z" ,"value":  "z0d4mgr12t" ,"key":  "2216cq14oc" },{"id":  "9a1db565-d210-4ec7-9a8d-27f92f0ed7e6" ,"createdAt":  "2021-11-08T22:14:25.000Z" ,"updatedAt":  "2022-08-22T19:26:48.000Z" ,"value":  "apqspk9j88" ,"key":  "g8gpmsvgo2" },{"id":  "7d1dbe63-93ec-4a71-8c92-ef5674889b5f" ,"createdAt":  "2022-10-29T11:20:55.000Z" ,"updatedAt":  "2023-06-13T05:26:49.000Z" ,"value":  "qaxnbw5oyh" ,"key":  "wsp9ildulq" },{"id":  "34c18e05-2582-4c11-9f8d-5c729531ff73" ,"createdAt":  "2022-09-12T20:29:32.000Z" ,"updatedAt":  "2023-05-01T06:41:12.000Z" ,"value":  "7vffe419if" ,"key":  "eblz8c1bm4" },{"id":  "20905f35-87c1-4004-bc83-16cb72903664" ,"createdAt":  "2023-03-13T08:22:47.000Z" ,"updatedAt":  "2022-01-20T04:08:09.000Z" ,"value":  "2cyh042huz" ,"key":  "yq7r2978ma" },{"id":  "a3c0745a-6bca-43e8-a04d-bf2dc2ca7114" ,"createdAt":  "2022-06-13T15:13:47.000Z" ,"updatedAt":  "2023-04-04T07:56:12.000Z" ,"value":  "zc3syynta1" ,"key":  "2oes3t37m8" },{"id":  "6e954718-6a7c-47ea-bdd4-98caa7a2baef" ,"createdAt":  "2023-03-06T10:52:21.000Z" ,"updatedAt":  "2021-11-24T15:08:25.000Z" ,"value":  "snf7l53s7n" ,"key":  "wvw1cpn85z" },{"id":  "3b83b5c0-ee48-4b59-8be5-a890618255fa" ,"createdAt":  "2023-06-29T14:24:19.000Z" ,"updatedAt":  "2023-02-16T12:31:45.000Z" ,"value":  "2fdhfi583q" ,"key":  "op39i6lil4" },{"id":  "3a5d06c2-791f-48cf-8bf0-5c2adcbdff25" ,"createdAt":  "2022-06-21T06:00:45.000Z" ,"updatedAt":  "2022-02-07T12:03:07.000Z" ,"value":  "fzmegp955k" ,"key":  "yi74i634vb" },{"id":  "f952a8bc-3ea1-4cd0-a62d-4b35ee7ba580" ,"createdAt":  "2023-01-21T07:19:18.000Z" ,"updatedAt":  "2022-07-28T16:19:16.000Z" ,"value":  "8pyilg4pxs" ,"key":  "qh3351ww6d" },{"id":  "71b9bebb-2816-4d55-ba69-ca9eb42a316b" ,"createdAt":  "2023-07-08T00:42:03.000Z" ,"updatedAt":  "2022-02-16T19:36:29.000Z" ,"value":  "bropjc851u" ,"key":  "w1cap0ggfc" },{"id":  "9f81f3aa-22f8-4baf-87c9-178c761f4bfa" ,"createdAt":  "2022-08-10T09:21:46.000Z" ,"updatedAt":  "2022-01-05T01:00:35.000Z" ,"value":  "p1alpzt2sa" ,"key":  "5rsh3h6tim" },{"id":  "9b6143cd-0c01-4fe0-a503-be8ef000c946" ,"createdAt":  "2023-02-24T12:58:06.000Z" ,"updatedAt":  "2023-07-02T19:52:51.000Z" ,"value":  "ajvucormuc" ,"key":  "3wkwvxo03r" },{"id":  "4acfdd8b-9878-4bcf-a09a-3bfef97e8c49" ,"createdAt":  "2022-09-08T03:02:34.000Z" ,"updatedAt":  "2022-09-01T10:43:37.000Z" ,"value":  "fqk7fdlxle" ,"key":  "fidc7us31f" },{"id":  "45044184-5317-4b28-8637-c864563e5a84" ,"createdAt":  "2022-04-09T02:21:34.000Z" ,"updatedAt":  "2022-02-08T18:17:18.000Z" ,"value":  "kvn2hurj3u" ,"key":  "huc878ok46" },{"id":  "092f5e52-9329-42a1-834d-2509933f91da" ,"createdAt":  "2022-11-27T16:54:15.000Z" ,"updatedAt":  "2022-11-17T10:59:56.000Z" ,"value":  "7byr5k8u9b" ,"key":  "4wckyw461v" },{"id":  "d3fc978e-017c-48a9-9fd8-87f4e763d1a3" ,"createdAt":  "2023-04-27T00:53:30.000Z" ,"updatedAt":  "2022-10-19T06:26:36.000Z" ,"value":  "izufalw0w9" ,"key":  "lsocijyas4" },{"id":  "982a837d-2298-41ff-bd29-f4f1218848a7" ,"createdAt":  "2022-10-22T04:23:40.000Z" ,"updatedAt":  "2023-03-25T12:59:31.000Z" ,"value":  "pzpteqkjev" ,"key":  "7u1wfa3uyh" },{"id":  "b4f17035-2493-4163-9c72-1c815a241917" ,"createdAt":  "2023-08-04T19:47:25.000Z" ,"updatedAt":  "2022-02-08T05:05:58.000Z" ,"value":  "fjekrwkhav" ,"key":  "cbrit57c6c" },{"id":  "69a264f2-d651-4b78-83c6-4c4d665a722c" ,"createdAt":  "2023-04-07T00:38:02.000Z" ,"updatedAt":  "2023-09-16T09:39:44.000Z" ,"value":  "u5tzk2go30" ,"key":  "y68zkpnosz" },{"id":  "d5ccb6cb-7668-4bdb-b3bb-af055f4bf33e" ,"createdAt":  "2022-08-14T14:27:07.000Z" ,"updatedAt":  "2022-07-11T06:55:27.000Z" ,"value":  "8sc6s84fv8" ,"key":  "0opivnkirz" },{"id":  "bce25dc8-4ea1-4387-ad88-1eecf9165dcd" ,"createdAt":  "2022-02-10T18:22:46.000Z" ,"updatedAt":  "2022-03-09T07:54:20.000Z" ,"value":  "gc645fqsfn" ,"key":  "ws5ksb71qe" },{"id":  "72eb7c65-02ab-42c6-a218-a577236b8b0e" ,"createdAt":  "2023-01-03T20:02:06.000Z" ,"updatedAt":  "2022-02-17T01:24:47.000Z" ,"value":  "3xo79rndbz" ,"key":  "5nm0k0ho2g" },{"id":  "7fcbdca7-1794-49fb-a121-14c7a5997e25" ,"createdAt":  "2022-05-29T10:50:05.000Z" ,"updatedAt":  "2023-04-30T18:02:33.000Z" ,"value":  "x4nlp1xmel" ,"key":  "wx64bpdnkq" },{"id":  "28eef013-e8ed-4ac0-bdf4-9e17fb6e0d65" ,"createdAt":  "2021-11-07T13:16:18.000Z" ,"updatedAt":  "2023-08-26T00:50:13.000Z" ,"value":  "g2ns29p76f" ,"key":  "kvu1z8kb0g" },{"id":  "3fb789d2-f5c7-43d9-b062-97edd22eac2c" ,"createdAt":  "2021-12-11T04:04:59.000Z" ,"updatedAt":  "2023-01-11T00:10:11.000Z" ,"value":  "rj0qgrvkr2" ,"key":  "p49uofj4eg" },{"id":  "9a7a9fb7-719d-4cf6-8a23-f95a6ce7c530" ,"createdAt":  "2023-05-02T09:58:40.000Z" ,"updatedAt":  "2021-12-13T11:12:44.000Z" ,"value":  "7rnpkfbtz8" ,"key":  "7nuk7i6t81" },{"id":  "58ced655-32d4-487a-a4e2-b17770497269" ,"createdAt":  "2022-05-25T09:01:03.000Z" ,"updatedAt":  "2022-03-26T12:15:14.000Z" ,"value":  "h9vl75sqvt" ,"key":  "lgrwq4283x" },{"id":  "d8406869-90f8-43b5-a369-b21688cb9aa9" ,"createdAt":  "2022-10-16T23:19:50.000Z" ,"updatedAt":  "2022-11-13T05:16:26.000Z" ,"value":  "gmuo2qhwwd" ,"key":  "idx6mf7neq" },{"id":  "df6d9b9c-2795-4aad-ac3d-c07c6e510029" ,"createdAt":  "2021-11-11T03:49:02.000Z" ,"updatedAt":  "2022-01-15T01:09:03.000Z" ,"value":  "alam0kzy1l" ,"key":  "zho48nxcti" },{"id":  "e3714c6b-837b-4e9e-b975-b5bf4d7a7b62" ,"createdAt":  "2022-08-05T02:13:27.000Z" ,"updatedAt":  "2023-02-11T12:37:44.000Z" ,"value":  "i84uvttebl" ,"key":  "m56e92fgav" },{"id":  "e5238fb4-07fe-4577-b969-5e68a52b5360" ,"createdAt":  "2021-11-22T18:39:16.000Z" ,"updatedAt":  "2022-06-10T20:31:35.000Z" ,"value":  "m8cfgozsry" ,"key":  "w2bc1zwwpb" },{"id":  "6679a211-1c7a-4c25-b73c-7be27e645841" ,"createdAt":  "2023-04-21T05:07:07.000Z" ,"updatedAt":  "2022-01-09T00:44:20.000Z" ,"value":  "ay20jg9u9j" ,"key":  "ybjleu9uxu" },{"id":  "3bf923db-3f8f-4157-9072-83d0c5c74ccb" ,"createdAt":  "2022-09-10T16:50:29.000Z" ,"updatedAt":  "2022-03-02T15:04:51.000Z" ,"value":  "2a14k69vwx" ,"key":  "o2bp1w0xih" },{"id":  "b96a5c5b-ba1d-4225-990f-df71bffee712" ,"createdAt":  "2022-05-31T19:46:56.000Z" ,"updatedAt":  "2022-12-10T13:11:56.000Z" ,"value":  "6r5e5vukc3" ,"key":  "zt3nz5um2t" },{"id":  "70251cb0-808d-4afc-bfd5-6bbb0cc9f445" ,"createdAt":  "2023-05-07T09:13:23.000Z" ,"updatedAt":  "2023-02-07T13:21:55.000Z" ,"value":  "s69qgid1b2" ,"key":  "z92f6gday1" },{"id":  "94a88010-6f6f-4d73-8759-cfb383e94fef" ,"createdAt":  "2023-09-24T07:44:17.000Z" ,"updatedAt":  "2022-06-10T00:00:53.000Z" ,"value":  "l436jpdiu5" ,"key":  "483gyh46ep" },{"id":  "d1904d95-e93b-4a61-9c63-8c7c0f50788c" ,"createdAt":  "2022-11-13T03:22:36.000Z" ,"updatedAt":  "2022-01-24T09:09:47.000Z" ,"value":  "no0j8bo0wl" ,"key":  "1ccjagkwu5" },{"id":  "01cf9e89-cd72-44cc-98cc-c10dbbdb8461" ,"createdAt":  "2022-06-19T22:28:36.000Z" ,"updatedAt":  "2023-03-09T22:53:02.000Z" ,"value":  "0mfzz379xq" ,"key":  "8b57w1wsob" },{"id":  "ce7c1c92-63b8-42f6-9a40-c794025d88a7" ,"createdAt":  "2022-09-19T15:09:50.000Z" ,"updatedAt":  "2023-06-01T03:57:21.000Z" ,"value":  "g9avxqs7db" ,"key":  "umnv5ak0ol" },{"id":  "850f2c0e-0dae-4be1-90b6-736eb768af7e" ,"createdAt":  "2023-09-10T11:32:59.000Z" ,"updatedAt":  "2023-03-16T01:25:41.000Z" ,"value":  "pe1zpwodk0" ,"key":  "g3c85kwzl8" },{"id":  "d5401410-482e-4690-b517-adc939940475" ,"createdAt":  "2022-11-15T20:33:47.000Z" ,"updatedAt":  "2023-06-05T19:21:00.000Z" ,"value":  "eykzr94yoe" ,"key":  "3l1rq9ppbo" },{"id":  "ddc77ae8-6e9f-4460-a26e-dc083ebd33cd" ,"createdAt":  "2022-05-12T05:45:33.000Z" ,"updatedAt":  "2023-06-26T14:19:12.000Z" ,"value":  "b03761wk2k" ,"key":  "bl0x30o0yh" },{"id":  "c56018a5-bea6-4045-9319-d3d0fe4d7f9e" ,"createdAt":  "2022-02-18T03:52:08.000Z" ,"updatedAt":  "2022-04-04T10:36:57.000Z" ,"value":  "u4u4kz22vk" ,"key":  "t5aw569kz5" },{"id":  "7b37a1d5-700b-4ac1-a588-2902024e35f4" ,"createdAt":  "2022-12-23T00:55:40.000Z" ,"updatedAt":  "2022-11-06T09:29:43.000Z" ,"value":  "w7uyqc0apd" ,"key":  "ayp0ucvowl" },{"id":  "c115b587-5bf3-4052-b022-49d9acc28379" ,"createdAt":  "2023-04-15T00:30:24.000Z" ,"updatedAt":  "2023-09-20T20:07:24.000Z" ,"value":  "b6ue3qxzeo" ,"key":  "oo6okzgsi4" },{"id":  "2cee18af-4642-4edf-8bcd-ca038f7900d6" ,"createdAt":  "2022-02-09T08:57:37.000Z" ,"updatedAt":  "2022-05-16T03:27:52.000Z" ,"value":  "9fmlhjocsi" ,"key":  "iyq81tp8l5" },{"id":  "ca4b8b1c-9ffa-499e-abf3-94ec5706abb2" ,"createdAt":  "2023-10-08T14:06:04.000Z" ,"updatedAt":  "2022-05-07T22:44:31.000Z" ,"value":  "00aq5v4x2w" ,"key":  "e9x3ck2wmb" },{"id":  "96a56aa2-762d-45ec-857a-c902731e664a" ,"createdAt":  "2022-11-13T18:20:04.000Z" ,"updatedAt":  "2021-11-07T11:25:40.000Z" ,"value":  "hkfgzldltj" ,"key":  "d7nntnjot5" },{"id":  "461e886a-0760-404c-8670-f389ffebbe59" ,"createdAt":  "2022-11-20T08:20:54.000Z" ,"updatedAt":  "2022-02-08T10:56:34.000Z" ,"value":  "70q3fj35bp" ,"key":  "uyw29iaw6b" },{"id":  "78fe4fe6-04ee-479f-97ed-7a596fbdd909" ,"createdAt":  "2022-02-12T17:55:07.000Z" ,"updatedAt":  "2023-02-19T05:49:13.000Z" ,"value":  "os595q4asc" ,"key":  "4z8vwnzuc2" },{"id":  "3f937397-7d52-43f6-80b7-dca085775fef" ,"createdAt":  "2022-12-05T01:56:19.000Z" ,"updatedAt":  "2023-04-30T05:38:59.000Z" ,"value":  "034twfp3r8" ,"key":  "2ibqs5z4st" },{"id":  "aefaab75-05b4-42d2-a3cf-5357e7aa85b0" ,"createdAt":  "2021-12-05T11:59:20.000Z" ,"updatedAt":  "2023-01-14T12:21:27.000Z" ,"value":  "zwm9h957or" ,"key":  "hgnrg4rtay" },{"id":  "e80ad2c2-2e35-4340-a64a-7d27c0566949" ,"createdAt":  "2022-08-09T20:38:18.000Z" ,"updatedAt":  "2023-03-06T18:35:31.000Z" ,"value":  "vvfs74rtz8" ,"key":  "qmhoeupjaa" },{"id":  "edbd8ed7-a020-4b57-a388-8579d990c1e6" ,"createdAt":  "2023-01-10T03:57:53.000Z" ,"updatedAt":  "2022-01-22T15:44:54.000Z" ,"value":  "7a8ek4r6it" ,"key":  "qmbds9b5vl" },{"id":  "03428f4f-1fbb-4904-a352-16bc5c057f80" ,"createdAt":  "2023-05-02T01:32:30.000Z" ,"updatedAt":  "2022-10-25T06:47:01.000Z" ,"value":  "bwcuv77rfv" ,"key":  "upi29v4i3w" },{"id":  "538da674-3f88-40e0-a2d8-66e8d2e4c37c" ,"createdAt":  "2022-11-30T14:50:36.000Z" ,"updatedAt":  "2023-04-03T02:25:08.000Z" ,"value":  "3neshdgntg" ,"key":  "f5fsiz18dc" },{"id":  "99e70113-b374-4163-acc8-3ee0d9f68e2d" ,"createdAt":  "2021-12-12T04:46:11.000Z" ,"updatedAt":  "2022-02-04T13:18:44.000Z" ,"value":  "26cclc781y" ,"key":  "kvhsffbltd" },{"id":  "bae5f794-67f0-48cb-bfc9-ceff9c476401" ,"createdAt":  "2022-10-26T10:43:07.000Z" ,"updatedAt":  "2022-08-07T10:14:46.000Z" ,"value":  "4ikhrjm1g5" ,"key":  "bzj5yytmff" },{"id":  "7627a007-6a25-49f7-bd10-2ca6660e7bd6" ,"createdAt":  "2022-05-30T14:56:05.000Z" ,"updatedAt":  "2021-10-30T17:44:02.000Z" ,"value":  "medywrgxsq" ,"key":  "cjd7xzkjdo" },{"id":  "c710fbed-2a1a-42df-a197-f306b3dd89ef" ,"createdAt":  "2023-08-18T02:57:02.000Z" ,"updatedAt":  "2022-11-06T12:26:32.000Z" ,"value":  "6q8ow1mfko" ,"key":  "bo23tzoyz4" },{"id":  "c2619b6c-3198-4651-933b-78b8a79aa8c8" ,"createdAt":  "2023-05-01T13:05:28.000Z" ,"updatedAt":  "2022-11-19T00:06:39.000Z" ,"value":  "aox25wueby" ,"key":  "zkrdqm66ou" },{"id":  "f8d26465-11a6-4652-92d2-9c08a0670f35" ,"createdAt":  "2022-07-01T13:10:35.000Z" ,"updatedAt":  "2022-03-22T19:30:33.000Z" ,"value":  "ykopfaqo8w" ,"key":  "zgfnx8za5p" },{"id":  "1464e620-3458-4706-8734-3039674d67cd" ,"createdAt":  "2022-02-01T09:14:21.000Z" ,"updatedAt":  "2023-01-23T16:59:46.000Z" ,"value":  "yl5k0pyr1s" ,"key":  "78gilg3pjp" },{"id":  "481e3ffa-50ac-4594-974a-a8b4b633d111" ,"createdAt":  "2021-12-19T14:29:15.000Z" ,"updatedAt":  "2023-10-07T15:40:50.000Z" ,"value":  "en5hx22s00" ,"key":  "hhoj4gtxwt" },{"id":  "4f607907-7eb3-4390-bc53-8ff04f5a0071" ,"createdAt":  "2022-03-04T13:14:53.000Z" ,"updatedAt":  "2022-05-19T15:45:19.000Z" ,"value":  "51uhj7at86" ,"key":  "tgqer4twvw" },{"id":  "ccf89933-d346-4835-b433-a272262df660" ,"createdAt":  "2022-07-22T22:22:23.000Z" ,"updatedAt":  "2023-01-24T14:12:41.000Z" ,"value":  "ahs0qpiwe4" ,"key":  "6qeounk76m" },{"id":  "08acd3c4-198b-41c5-83c9-50fdab147407" ,"createdAt":  "2022-07-01T08:14:49.000Z" ,"updatedAt":  "2022-11-02T22:47:51.000Z" ,"value":  "mnw7pog5l0" ,"key":  "d22wth2t99" },{"id":  "d516718e-3849-45e5-a9a0-445424c4f1b6" ,"createdAt":  "2022-10-07T22:51:38.000Z" ,"updatedAt":  "2022-03-11T01:35:26.000Z" ,"value":  "vgvkbqz1wn" ,"key":  "cgduwz3y4v" },{"id":  "e70c0789-fa1c-4875-96f5-362e5fae6219" ,"createdAt":  "2022-03-16T10:25:16.000Z" ,"updatedAt":  "2021-11-19T20:47:32.000Z" ,"value":  "t4m7tqxycc" ,"key":  "4u1o0oqduz" },{"id":  "40131c8a-82e7-4adf-a2fc-a83f299f4658" ,"createdAt":  "2023-09-08T02:49:56.000Z" ,"updatedAt":  "2022-10-05T19:20:59.000Z" ,"value":  "wpigjyzof5" ,"key":  "pdk3b0alpo" },{"id":  "bf038372-bb1a-4ba0-9b5d-4a6e00410bf8" ,"createdAt":  "2023-04-16T04:43:00.000Z" ,"updatedAt":  "2022-11-24T23:16:22.000Z" ,"value":  "bdgke6bw0u" ,"key":  "phokqy7jpi" }]}